{
  "updated_at": "2026-06-21T10:55:45+00:00",
  "items": [
    {
      "title": "Berkshire Hathaway's Greg Abel Dumps Amazon and Loads Up on Alphabet. Is It the Better Buy?",
      "link": "https://www.fool.com/investing/2026/06/21/berkshire-hathaways-greg-abel-dumps-amazon-and-loa/?.tsrc=rss",
      "source": "Yahoo Finance",
      "published": "2026-06-21T10:32:00+00:00"
    },
    {
      "title": "Why Bitcoin's Best Days May Still Be Ahead of It",
      "link": "https://www.fool.com/investing/2026/06/21/why-bitcoins-best-days-may-still-be-ahead-of-it/?.tsrc=rss",
      "source": "Yahoo Finance",
      "published": "2026-06-21T10:27:00+00:00"
    },
    {
      "title": "Intuitive Machines' Big Cash Grab Isn't as Scary as It Looks",
      "link": "https://www.fool.com/investing/2026/06/21/intuitive-machines-big-cash-grab-isnt-scary/?.tsrc=rss",
      "source": "Yahoo Finance",
      "published": "2026-06-21T10:26:00+00:00"
    },
    {
      "title": "SpaceX IPO: Here's Why Another $20 Billion Capital Raise Is on the Way",
      "link": "https://www.fool.com/investing/2026/06/21/spacex-ipo-heres-why-another-20-billion-capital-ra/?.tsrc=rss",
      "source": "Yahoo Finance",
      "published": "2026-06-21T10:25:00+00:00"
    },
    {
      "title": "The Crowd Is Selling Coca-Cola. Here's Why I'd Be Buying the Dip.",
      "link": "https://www.fool.com/investing/2026/06/21/crowd-selling-coca-cola-stock-why-buy-dip/?.tsrc=rss",
      "source": "Yahoo Finance",
      "published": "2026-06-21T10:10:00+00:00"
    },
    {
      "title": "Nvidia (NVDA) Stock Weighs AI Momentum Against Mixed Valuation Signals After 46% One-Year Gain",
      "link": "https://finance.yahoo.com/markets/stocks/articles/nvidia-nvda-stock-weighs-ai-100834813.html?.tsrc=rss",
      "source": "Yahoo Finance",
      "published": "2026-06-21T10:08:34+00:00"
    },
    {
      "title": "Dutch Bros Doubled Over the Last 3 Years. Can It Triple by 2030?",
      "link": "https://www.fool.com/investing/2026/06/21/dutch-bros-doubled-over-the-last-3-years-can-it-tr/?.tsrc=rss",
      "source": "Yahoo Finance",
      "published": "2026-06-21T09:55:00+00:00"
    },
    {
      "title": "Social Security COLA Estimates for 2027 Are Getting a \"Trump Bump\": Here's How Much Extra You Could Receive",
      "link": "https://www.fool.com/retirement/2026/06/21/social-security-cola-estimates-for-2027-are-gettin/?.tsrc=rss",
      "source": "Yahoo Finance",
      "published": "2026-06-21T09:27:00+00:00"
    },
    {
      "title": "1 Big Catalyst for Costco Stock Right Now",
      "link": "https://www.fool.com/investing/2026/06/21/1-big-catalyst-for-costco-stock-right-now/?.tsrc=rss",
      "source": "Yahoo Finance",
      "published": "2026-06-21T09:25:00+00:00"
    },
    {
      "title": "Prediction: Here's How Much SpaceX Will Be Worth by the End of 2026",
      "link": "https://www.fool.com/investing/2026/06/21/prediction-heres-how-much-spacex-will-be-worth-by/?.tsrc=rss",
      "source": "Yahoo Finance",
      "published": "2026-06-21T09:04:00+00:00"
    },
    {
      "title": "Want to Retire on $500,000? 3 Stocks to Buy and Never Sell",
      "link": "https://www.fool.com/investing/2026/06/21/want-to-retire-on-500000-3-stocks-to-buy-and-never/?.tsrc=rss",
      "source": "Yahoo Finance",
      "published": "2026-06-21T08:44:00+00:00"
    },
    {
      "title": "Social Security Benefit Cuts Are Only 6 Years Away, Thanks in Part to President Donald Trump",
      "link": "https://www.fool.com/retirement/2026/06/21/social-security-benefit-cuts-6-years-away-trump/?.tsrc=rss",
      "source": "Yahoo Finance",
      "published": "2026-06-21T08:26:00+00:00"
    },
    {
      "title": "3 Reasons Why Netflix Is Down 31% Since Completing Its 10-For-1 Stock Split",
      "link": "https://www.fool.com/investing/2026/06/21/3-reasons-why-netflix-is-down-31-since-completing/?.tsrc=rss",
      "source": "Yahoo Finance",
      "published": "2026-06-21T08:25:00+00:00"
    },
    {
      "title": "Will Nvidia Stock Soar After June 24? The Evidence is Piling Up and Here's What It Shows",
      "link": "https://www.fool.com/investing/2026/06/21/will-nvidia-stock-soar-after-june-24-the-evidence/?.tsrc=rss",
      "source": "Yahoo Finance",
      "published": "2026-06-21T08:23:00+00:00"
    },
    {
      "title": "Why Hormuz and trade tensions could revive in 2027",
      "link": "https://finance.yahoo.com/energy/articles/why-hormuz-trade-tensions-could-081848688.html?.tsrc=rss",
      "source": "Yahoo Finance",
      "published": "2026-06-21T08:18:48+00:00"
    },
    {
      "title": "Is It Too Late to Buy Palantir Stock? Here Is What Its Valuation Says About Its Future.",
      "link": "https://www.fool.com/investing/2026/06/21/too-late-buy-palantir-stock-what-valuation-future/?.tsrc=rss",
      "source": "Yahoo Finance",
      "published": "2026-06-21T08:15:00+00:00"
    },
    {
      "title": "If You'd Invested $10,000 in Dogecoin 10 Years Ago, Here's How Much You'd Have Today",
      "link": "https://www.fool.com/investing/2026/06/21/you-invested-10000-dogecoin-10-years-ago-how-much/?.tsrc=rss",
      "source": "Yahoo Finance",
      "published": "2026-06-21T07:50:00+00:00"
    },
    {
      "title": "Bitdeer Mines 921 BTC as Smaller Bitcoin Stash Raises AI Pivot Question",
      "link": "https://www.cryptoprowl.com/releases/bitdeer-mines-921-btc-as-smaller-bitcoin-stash-raises-ai-pivot-question-5935?.tsrc=rss",
      "source": "Yahoo Finance",
      "published": "2026-06-21T07:27:00+00:00"
    },
    {
      "title": "3 Monster Dividend Stocks to Hold for the Next 10 Years",
      "link": "https://www.fool.com/investing/2026/06/21/3-monster-dividend-stocks-to-hold-for-the-next-10/?.tsrc=rss",
      "source": "Yahoo Finance",
      "published": "2026-06-21T07:25:00+00:00"
    },
    {
      "title": "Better S&P 500 ETF: VOO vs. SPY",
      "link": "https://www.fool.com/investing/2026/06/21/better-sp-500-etf-voo-vs-spy/?.tsrc=rss",
      "source": "Yahoo Finance",
      "published": "2026-06-21T07:20:00+00:00"
    }
  ]
}